README.md
setup.cfg
setup.py
accesspanel/__init__.py
accesspanel/accesspanel.py
accesspanel.egg-info/PKG-INFO
accesspanel.egg-info/SOURCES.txt
accesspanel.egg-info/dependency_links.txt
accesspanel.egg-info/top_level.txt
accesspanel/extensions/__init__.py
accesspanel/extensions/ansi.py
accesspanel/extensions/base.py
accesspanel/extensions/history.py
accesspanel/extensions/lock_input.py