Metadata-Version: 1.0
Name: accesspanel
Version: 0.18
Summary: AccessPanel is a module to enhance accessibility though a set of
Home-page: https://github.com/vlegoff/accesspanel
Author: Vincent Le Goff
Author-email: vincent.legoff.srs@gmail.com
License: UNKNOWN
Keywords: accessibility
Platform: UNKNOWN
